alomancy/__init__.py
alomancy/version.py
alomancy/analysis/__init__.py
alomancy/analysis/example_committee_al_loop_mae_plot.png
alomancy/analysis/plotting.py
alomancy/configs/__init__.py
alomancy/configs/config_dictionaries.py
alomancy/configs/remote_info.py
alomancy/core/__init__.py
alomancy/core/base_active_learning.py
alomancy/core/standard_active_learning.py
alomancy/high_accuracy_evaluation/dft/__init__.py
alomancy/high_accuracy_evaluation/dft/qe_remote_submitter.py
alomancy/high_accuracy_evaluation/dft/run_qe.py
alomancy/mlip/__init__.py
alomancy/mlip/committee_remote_submitter.py
alomancy/mlip/get_mace_eval_info.py
alomancy/mlip/mace_wfl.py
alomancy/structure_generation/__init__.py
alomancy/structure_generation/find_high_sd_structures.py
alomancy/structure_generation/select_initial_structures.py
alomancy/structure_generation/md/__init__.py
alomancy/structure_generation/md/generate_structures.py
alomancy/structure_generation/md/md_remote_submitter.py
alomancy/structure_generation/md/md_wfl.py
alomancy/utils/__init__.py
alomancy/utils/clean_structures.py
alomancy/utils/remote_job_executor.py
alomancy/utils/test_train_manager.py
alomancy-0.1.1.dist-info/METADATA
alomancy-0.1.1.dist-info/WHEEL
alomancy-0.1.1.dist-info/top_level.txt
alomancy-0.1.1.dist-info/RECORD
